{
  "resultType": "matrix",
  "result": [
    {
      "metric": {
        "device": "Power",
        "instance": "plug_monit:8000",
        "job": "plug_monitor"
      },
      "values": [
        [
          1719816375.028,
          "58.7"
        ],
        [
          1719816375.528,
          "58.7"
        ],
        [
          1719816376.028,
          "58.7"
        ],
        [
          1719816376.528,
          "58.7"
        ],
        [
          1719816377.028,
          "58.9"
        ],
        [
          1719816377.528,
          "58.9"
        ],
        [
          1719816378.028,
          "58.9"
        ],
        [
          1719816378.528,
          "58.9"
        ],
        [
          1719816379.028,
          "57.6"
        ],
        [
          1719816379.528,
          "57.6"
        ],
        [
          1719816380.028,
          "57.6"
        ],
        [
          1719816380.528,
          "57.6"
        ],
        [
          1719816381.028,
          "58.4"
        ],
        [
          1719816381.528,
          "58.4"
        ],
        [
          1719816382.028,
          "58.4"
        ],
        [
          1719816382.528,
          "58.4"
        ],
        [
          1719816383.028,
          "59"
        ],
        [
          1719816383.528,
          "59"
        ],
        [
          1719816384.028,
          "59"
        ],
        [
          1719816384.528,
          "59"
        ],
        [
          1719816385.028,
          "59"
        ],
        [
          1719816385.528,
          "59"
        ],
        [
          1719816386.028,
          "59"
        ],
        [
          1719816386.528,
          "59"
        ],
        [
          1719816387.028,
          "59"
        ],
        [
          1719816387.528,
          "59"
        ],
        [
          1719816388.028,
          "58.6"
        ],
        [
          1719816388.528,
          "58.6"
        ],
        [
          1719816389.028,
          "59.2"
        ],
        [
          1719816389.528,
          "59.2"
        ],
        [
          1719816390.028,
          "59.2"
        ],
        [
          1719816390.528,
          "59.2"
        ],
        [
          1719816391.028,
          "58.7"
        ],
        [
          1719816391.528,
          "58.7"
        ],
        [
          1719816392.028,
          "58.7"
        ],
        [
          1719816392.528,
          "58.7"
        ],
        [
          1719816393.028,
          "59.3"
        ],
        [
          1719816393.528,
          "59.3"
        ],
        [
          1719816394.028,
          "59.3"
        ],
        [
          1719816394.528,
          "59.3"
        ],
        [
          1719816395.028,
          "59.3"
        ],
        [
          1719816395.528,
          "59.3"
        ],
        [
          1719816396.028,
          "59.3"
        ],
        [
          1719816396.528,
          "59.3"
        ],
        [
          1719816397.028,
          "59.3"
        ],
        [
          1719816397.528,
          "59.3"
        ],
        [
          1719816398.028,
          "59.3"
        ],
        [
          1719816398.528,
          "59.3"
        ],
        [
          1719816399.028,
          "57.6"
        ],
        [
          1719816399.528,
          "57.6"
        ],
        [
          1719816400.028,
          "57.6"
        ],
        [
          1719816400.528,
          "57.6"
        ],
        [
          1719816401.028,
          "58.5"
        ],
        [
          1719816401.528,
          "58.5"
        ],
        [
          1719816402.028,
          "58.5"
        ],
        [
          1719816402.528,
          "58.5"
        ],
        [
          1719816403.028,
          "58.4"
        ],
        [
          1719816403.528,
          "58.4"
        ],
        [
          1719816404.028,
          "58.4"
        ],
        [
          1719816404.528,
          "58.4"
        ],
        [
          1719816405.028,
          "58.4"
        ],
        [
          1719816405.528,
          "58.5"
        ],
        [
          1719816406.028,
          "58.5"
        ],
        [
          1719816406.528,
          "58.5"
        ],
        [
          1719816407.028,
          "58.5"
        ],
        [
          1719816407.528,
          "58.5"
        ],
        [
          1719816408.028,
          "58.5"
        ],
        [
          1719816408.528,
          "58.5"
        ],
        [
          1719816409.028,
          "58.5"
        ],
        [
          1719816409.528,
          "57.9"
        ],
        [
          1719816410.028,
          "57.9"
        ],
        [
          1719816410.528,
          "57.9"
        ],
        [
          1719816411.028,
          "57.9"
        ],
        [
          1719816411.528,
          "57.5"
        ],
        [
          1719816412.028,
          "57.5"
        ],
        [
          1719816412.528,
          "57.5"
        ],
        [
          1719816413.028,
          "57.5"
        ],
        [
          1719816413.528,
          "59.4"
        ],
        [
          1719816414.028,
          "59.4"
        ],
        [
          1719816414.528,
          "59.4"
        ],
        [
          1719816415.028,
          "59.4"
        ],
        [
          1719816415.528,
          "60.1"
        ],
        [
          1719816416.028,
          "60.1"
        ],
        [
          1719816416.528,
          "60.1"
        ],
        [
          1719816417.028,
          "60.1"
        ],
        [
          1719816417.528,
          "60.1"
        ],
        [
          1719816418.028,
          "60.1"
        ],
        [
          1719816418.528,
          "60.1"
        ],
        [
          1719816419.028,
          "60.1"
        ],
        [
          1719816419.528,
          "60.1"
        ],
        [
          1719816420.028,
          "60.1"
        ],
        [
          1719816420.528,
          "60.1"
        ],
        [
          1719816421.028,
          "60.1"
        ],
        [
          1719816421.528,
          "60.1"
        ],
        [
          1719816422.028,
          "60.1"
        ],
        [
          1719816422.528,
          "60.1"
        ],
        [
          1719816423.028,
          "60.1"
        ],
        [
          1719816423.528,
          "58.9"
        ],
        [
          1719816424.028,
          "58.9"
        ],
        [
          1719816424.528,
          "58.9"
        ],
        [
          1719816425.028,
          "58.9"
        ],
        [
          1719816425.528,
          "59"
        ],
        [
          1719816426.028,
          "59"
        ],
        [
          1719816426.528,
          "59"
        ],
        [
          1719816427.028,
          "59"
        ],
        [
          1719816427.528,
          "59.8"
        ],
        [
          1719816428.028,
          "59.8"
        ],
        [
          1719816428.528,
          "59.8"
        ],
        [
          1719816429.028,
          "59.8"
        ],
        [
          1719816429.528,
          "59.8"
        ],
        [
          1719816430.028,
          "59.8"
        ],
        [
          1719816430.528,
          "59.8"
        ],
        [
          1719816431.028,
          "59.8"
        ],
        [
          1719816431.528,
          "39.5"
        ],
        [
          1719816432.028,
          "39.5"
        ],
        [
          1719816432.528,
          "39.5"
        ],
        [
          1719816433.028,
          "39.5"
        ],
        [
          1719816433.528,
          "39.4"
        ],
        [
          1719816434.028,
          "39.4"
        ],
        [
          1719816434.528,
          "39.4"
        ],
        [
          1719816435.028,
          "39.4"
        ],
        [
          1719816435.528,
          "39.4"
        ],
        [
          1719816436.028,
          "39.4"
        ],
        [
          1719816436.528,
          "39.4"
        ],
        [
          1719816437.028,
          "39.7"
        ],
        [
          1719816437.528,
          "39.7"
        ],
        [
          1719816438.028,
          "39"
        ],
        [
          1719816438.528,
          "39"
        ],
        [
          1719816439.028,
          "39"
        ],
        [
          1719816439.528,
          "39"
        ],
        [
          1719816440.028,
          "39"
        ],
        [
          1719816440.528,
          "39"
        ],
        [
          1719816441.028,
          "39"
        ],
        [
          1719816441.528,
          "39"
        ],
        [
          1719816442.028,
          "39"
        ],
        [
          1719816442.528,
          "39"
        ],
        [
          1719816443.028,
          "39"
        ],
        [
          1719816443.528,
          "39"
        ],
        [
          1719816444.028,
          "39"
        ],
        [
          1719816444.528,
          "39"
        ],
        [
          1719816445.028,
          "38.8"
        ],
        [
          1719816445.528,
          "38.8"
        ],
        [
          1719816446.028,
          "39.5"
        ],
        [
          1719816446.528,
          "39.5"
        ],
        [
          1719816447.028,
          "39.5"
        ],
        [
          1719816447.528,
          "39.5"
        ],
        [
          1719816448.028,
          "39.5"
        ],
        [
          1719816448.528,
          "39.5"
        ],
        [
          1719816449.028,
          "40"
        ],
        [
          1719816449.528,
          "40"
        ],
        [
          1719816450.028,
          "40"
        ],
        [
          1719816450.528,
          "40"
        ],
        [
          1719816451.028,
          "40"
        ],
        [
          1719816451.528,
          "40"
        ],
        [
          1719816452.028,
          "38.8"
        ],
        [
          1719816452.528,
          "38.8"
        ],
        [
          1719816453.028,
          "38.8"
        ],
        [
          1719816453.528,
          "38.8"
        ],
        [
          1719816454.028,
          "39.4"
        ],
        [
          1719816454.528,
          "39.4"
        ],
        [
          1719816455.028,
          "39.4"
        ],
        [
          1719816455.528,
          "39.4"
        ],
        [
          1719816456.028,
          "39.4"
        ],
        [
          1719816456.528,
          "39.4"
        ],
        [
          1719816457.028,
          "39.4"
        ],
        [
          1719816457.528,
          "39.4"
        ],
        [
          1719816458.028,
          "39.4"
        ],
        [
          1719816458.528,
          "39.2"
        ],
        [
          1719816459.028,
          "39.2"
        ],
        [
          1719816459.528,
          "37.6"
        ],
        [
          1719816460.028,
          "37.6"
        ],
        [
          1719816460.528,
          "39.2"
        ],
        [
          1719816461.028,
          "39.2"
        ],
        [
          1719816461.528,
          "39.2"
        ],
        [
          1719816462.028,
          "39.2"
        ],
        [
          1719816462.528,
          "39.2"
        ],
        [
          1719816463.028,
          "39.2"
        ],
        [
          1719816463.528,
          "39.2"
        ],
        [
          1719816464.028,
          "39.2"
        ],
        [
          1719816464.528,
          "38.8"
        ],
        [
          1719816465.028,
          "38.8"
        ],
        [
          1719816465.528,
          "38.8"
        ],
        [
          1719816466.028,
          "38.8"
        ],
        [
          1719816466.528,
          "39.6"
        ],
        [
          1719816467.028,
          "39.6"
        ],
        [
          1719816467.528,
          "39.6"
        ],
        [
          1719816468.028,
          "39.6"
        ],
        [
          1719816468.528,
          "39.3"
        ],
        [
          1719816469.028,
          "39.3"
        ],
        [
          1719816469.528,
          "39.3"
        ],
        [
          1719816470.028,
          "39.3"
        ],
        [
          1719816470.528,
          "38.8"
        ],
        [
          1719816471.028,
          "38.8"
        ],
        [
          1719816471.528,
          "38.8"
        ],
        [
          1719816472.028,
          "38.8"
        ],
        [
          1719816472.528,
          "38.5"
        ],
        [
          1719816473.028,
          "38.5"
        ],
        [
          1719816473.528,
          "38.5"
        ],
        [
          1719816474.028,
          "38.5"
        ],
        [
          1719816474.528,
          "38.5"
        ],
        [
          1719816475.028,
          "38.5"
        ],
        [
          1719816475.528,
          "38.6"
        ],
        [
          1719816476.028,
          "38.6"
        ],
        [
          1719816476.528,
          "38.6"
        ],
        [
          1719816477.028,
          "38.6"
        ],
        [
          1719816477.528,
          "38.6"
        ],
        [
          1719816478.028,
          "39.3"
        ],
        [
          1719816478.528,
          "38.7"
        ],
        [
          1719816479.028,
          "38.7"
        ],
        [
          1719816479.528,
          "38.7"
        ],
        [
          1719816480.028,
          "38.7"
        ],
        [
          1719816480.528,
          "39.3"
        ],
        [
          1719816481.028,
          "39.3"
        ],
        [
          1719816481.528,
          "39.3"
        ],
        [
          1719816482.028,
          "39.3"
        ],
        [
          1719816482.528,
          "40.1"
        ],
        [
          1719816483.028,
          "40.1"
        ],
        [
          1719816483.528,
          "40.1"
        ],
        [
          1719816484.028,
          "40.1"
        ],
        [
          1719816484.528,
          "40.1"
        ],
        [
          1719816485.028,
          "40.1"
        ],
        [
          1719816485.528,
          "40.1"
        ],
        [
          1719816486.028,
          "40.1"
        ],
        [
          1719816486.528,
          "39.5"
        ],
        [
          1719816487.028,
          "39.5"
        ],
        [
          1719816487.528,
          "39.5"
        ],
        [
          1719816488.028,
          "39.5"
        ],
        [
          1719816488.528,
          "39.5"
        ],
        [
          1719816489.028,
          "39.9"
        ],
        [
          1719816489.528,
          "39.9"
        ],
        [
          1719816490.028,
          "39.9"
        ],
        [
          1719816490.528,
          "38.2"
        ],
        [
          1719816491.028,
          "38.2"
        ],
        [
          1719816491.528,
          "38.2"
        ],
        [
          1719816492.028,
          "38.2"
        ],
        [
          1719816492.528,
          "38.9"
        ],
        [
          1719816493.028,
          "38.9"
        ],
        [
          1719816493.528,
          "38.9"
        ],
        [
          1719816494.028,
          "38.9"
        ],
        [
          1719816494.528,
          "38.9"
        ],
        [
          1719816495.028,
          "38.9"
        ],
        [
          1719816495.528,
          "38.9"
        ],
        [
          1719816496.028,
          "38.9"
        ],
        [
          1719816496.528,
          "38.9"
        ],
        [
          1719816497.028,
          "38.9"
        ],
        [
          1719816497.528,
          "39.3"
        ],
        [
          1719816498.028,
          "39.3"
        ],
        [
          1719816498.528,
          "38.6"
        ],
        [
          1719816499.028,
          "38.6"
        ],
        [
          1719816499.528,
          "38.6"
        ],
        [
          1719816500.028,
          "38.6"
        ],
        [
          1719816500.528,
          "39.1"
        ],
        [
          1719816501.028,
          "39.1"
        ],
        [
          1719816501.528,
          "39.1"
        ],
        [
          1719816502.028,
          "39.1"
        ],
        [
          1719816502.528,
          "39.4"
        ],
        [
          1719816503.028,
          "39.4"
        ],
        [
          1719816503.528,
          "39.4"
        ],
        [
          1719816504.028,
          "39.4"
        ],
        [
          1719816504.528,
          "38.3"
        ],
        [
          1719816505.028,
          "38.3"
        ],
        [
          1719816505.528,
          "38.3"
        ],
        [
          1719816506.028,
          "38.3"
        ],
        [
          1719816506.528,
          "38.3"
        ],
        [
          1719816507.028,
          "38.3"
        ],
        [
          1719816507.528,
          "38.3"
        ],
        [
          1719816508.028,
          "38.3"
        ],
        [
          1719816508.528,
          "39.6"
        ],
        [
          1719816509.028,
          "39.6"
        ],
        [
          1719816509.528,
          "39.6"
        ],
        [
          1719816510.028,
          "39.6"
        ],
        [
          1719816510.528,
          "38.5"
        ],
        [
          1719816511.028,
          "38.5"
        ],
        [
          1719816511.528,
          "38.5"
        ],
        [
          1719816512.028,
          "38.5"
        ],
        [
          1719816512.528,
          "39"
        ],
        [
          1719816513.028,
          "39"
        ],
        [
          1719816513.528,
          "39"
        ],
        [
          1719816514.028,
          "39"
        ],
        [
          1719816514.528,
          "39.2"
        ],
        [
          1719816515.028,
          "39.2"
        ],
        [
          1719816515.528,
          "39.2"
        ],
        [
          1719816516.028,
          "39.2"
        ],
        [
          1719816516.528,
          "39.2"
        ],
        [
          1719816517.028,
          "39.2"
        ],
        [
          1719816517.528,
          "39.2"
        ],
        [
          1719816518.028,
          "39.2"
        ],
        [
          1719816518.528,
          "39.2"
        ],
        [
          1719816519.028,
          "39.2"
        ],
        [
          1719816519.528,
          "38.6"
        ],
        [
          1719816520.028,
          "38.6"
        ],
        [
          1719816520.528,
          "38.2"
        ],
        [
          1719816521.028,
          "38.2"
        ],
        [
          1719816521.528,
          "38.2"
        ],
        [
          1719816522.028,
          "38.2"
        ],
        [
          1719816522.528,
          "38.9"
        ],
        [
          1719816523.028,
          "38.9"
        ],
        [
          1719816523.528,
          "38.9"
        ],
        [
          1719816524.028,
          "38.9"
        ],
        [
          1719816524.528,
          "39"
        ],
        [
          1719816525.028,
          "39"
        ],
        [
          1719816525.528,
          "39"
        ],
        [
          1719816526.028,
          "39"
        ],
        [
          1719816526.528,
          "39.5"
        ],
        [
          1719816527.028,
          "39.5"
        ],
        [
          1719816527.528,
          "39.5"
        ],
        [
          1719816528.028,
          "39.5"
        ],
        [
          1719816528.528,
          "39.5"
        ],
        [
          1719816529.028,
          "39.5"
        ],
        [
          1719816529.528,
          "39.5"
        ],
        [
          1719816530.028,
          "39.5"
        ],
        [
          1719816530.528,
          "38.8"
        ],
        [
          1719816531.028,
          "38.8"
        ],
        [
          1719816531.528,
          "38.8"
        ],
        [
          1719816532.028,
          "38.8"
        ],
        [
          1719816532.528,
          "38.7"
        ],
        [
          1719816533.028,
          "38.7"
        ],
        [
          1719816533.528,
          "38.7"
        ],
        [
          1719816534.028,
          "38.7"
        ],
        [
          1719816534.528,
          "38.6"
        ],
        [
          1719816535.028,
          "38.6"
        ],
        [
          1719816535.528,
          "38.6"
        ],
        [
          1719816536.028,
          "38.6"
        ],
        [
          1719816536.528,
          "38.8"
        ],
        [
          1719816537.028,
          "38.8"
        ],
        [
          1719816537.528,
          "38.8"
        ],
        [
          1719816538.028,
          "38.8"
        ],
        [
          1719816538.528,
          "38.8"
        ],
        [
          1719816539.028,
          "38.8"
        ],
        [
          1719816539.528,
          "38.8"
        ],
        [
          1719816540.028,
          "38.8"
        ],
        [
          1719816540.528,
          "38.8"
        ],
        [
          1719816541.028,
          "38.8"
        ],
        [
          1719816541.528,
          "39.3"
        ],
        [
          1719816542.028,
          "39.3"
        ],
        [
          1719816542.528,
          "39.3"
        ],
        [
          1719816543.028,
          "39.6"
        ],
        [
          1719816543.528,
          "39.6"
        ],
        [
          1719816544.028,
          "39.6"
        ],
        [
          1719816544.528,
          "39.6"
        ],
        [
          1719816545.028,
          "39.1"
        ],
        [
          1719816545.528,
          "39.1"
        ],
        [
          1719816546.028,
          "39.1"
        ],
        [
          1719816546.528,
          "39.1"
        ],
        [
          1719816547.028,
          "39.2"
        ],
        [
          1719816547.528,
          "39.2"
        ],
        [
          1719816548.028,
          "39.2"
        ],
        [
          1719816548.528,
          "39.1"
        ],
        [
          1719816549.028,
          "39.1"
        ],
        [
          1719816549.528,
          "39.1"
        ],
        [
          1719816550.028,
          "39.1"
        ],
        [
          1719816550.528,
          "39.1"
        ],
        [
          1719816551.028,
          "39.1"
        ],
        [
          1719816551.528,
          "39.1"
        ],
        [
          1719816552.028,
          "39.1"
        ],
        [
          1719816552.528,
          "39.1"
        ],
        [
          1719816553.028,
          "39.1"
        ],
        [
          1719816553.528,
          "39.1"
        ],
        [
          1719816554.028,
          "39.1"
        ],
        [
          1719816554.528,
          "39.1"
        ],
        [
          1719816555.028,
          "39.3"
        ],
        [
          1719816555.528,
          "39.3"
        ],
        [
          1719816556.028,
          "39.3"
        ],
        [
          1719816556.528,
          "39.3"
        ],
        [
          1719816557.028,
          "39.1"
        ],
        [
          1719816557.528,
          "39.1"
        ],
        [
          1719816558.028,
          "39.1"
        ],
        [
          1719816558.528,
          "39.1"
        ],
        [
          1719816559.028,
          "39"
        ],
        [
          1719816559.528,
          "39"
        ],
        [
          1719816560.028,
          "39"
        ],
        [
          1719816560.528,
          "39"
        ],
        [
          1719816561.028,
          "39"
        ],
        [
          1719816561.528,
          "39"
        ],
        [
          1719816562.028,
          "39"
        ],
        [
          1719816562.528,
          "39"
        ],
        [
          1719816563.028,
          "39"
        ],
        [
          1719816563.528,
          "39"
        ],
        [
          1719816564.028,
          "38.8"
        ],
        [
          1719816564.528,
          "38.8"
        ],
        [
          1719816565.028,
          "38"
        ],
        [
          1719816565.528,
          "38"
        ],
        [
          1719816566.028,
          "38"
        ],
        [
          1719816566.528,
          "38"
        ],
        [
          1719816567.028,
          "39.6"
        ],
        [
          1719816567.528,
          "39.6"
        ],
        [
          1719816568.028,
          "39.6"
        ],
        [
          1719816568.528,
          "39.6"
        ],
        [
          1719816569.028,
          "38.9"
        ],
        [
          1719816569.528,
          "38.9"
        ],
        [
          1719816570.028,
          "38.9"
        ],
        [
          1719816570.528,
          "38.9"
        ],
        [
          1719816571.028,
          "38.9"
        ],
        [
          1719816571.528,
          "38.9"
        ],
        [
          1719816572.028,
          "38.9"
        ],
        [
          1719816572.528,
          "38.9"
        ],
        [
          1719816573.028,
          "38.9"
        ],
        [
          1719816573.528,
          "38.9"
        ],
        [
          1719816574.028,
          "38.9"
        ],
        [
          1719816574.528,
          "38.9"
        ],
        [
          1719816575.028,
          "39.5"
        ],
        [
          1719816575.528,
          "39.5"
        ],
        [
          1719816576.028,
          "39.5"
        ],
        [
          1719816576.528,
          "39.5"
        ],
        [
          1719816577.028,
          "38.5"
        ],
        [
          1719816577.528,
          "38.5"
        ],
        [
          1719816578.028,
          "38.5"
        ],
        [
          1719816578.528,
          "38.5"
        ],
        [
          1719816579.028,
          "38.7"
        ],
        [
          1719816579.528,
          "38.7"
        ],
        [
          1719816580.028,
          "38.7"
        ],
        [
          1719816580.528,
          "38.7"
        ],
        [
          1719816581.028,
          "38.8"
        ],
        [
          1719816581.528,
          "38.8"
        ],
        [
          1719816582.028,
          "38.8"
        ],
        [
          1719816582.528,
          "38.8"
        ],
        [
          1719816583.028,
          "38.8"
        ],
        [
          1719816583.528,
          "38.8"
        ],
        [
          1719816584.028,
          "38.8"
        ],
        [
          1719816584.528,
          "38.8"
        ],
        [
          1719816585.028,
          "38.8"
        ],
        [
          1719816585.528,
          "38.8"
        ],
        [
          1719816586.028,
          "39.3"
        ],
        [
          1719816586.528,
          "39.3"
        ],
        [
          1719816587.028,
          "39.6"
        ],
        [
          1719816587.528,
          "39.6"
        ],
        [
          1719816588.028,
          "39.6"
        ],
        [
          1719816588.528,
          "39.6"
        ],
        [
          1719816589.028,
          "39.3"
        ],
        [
          1719816589.528,
          "39.3"
        ],
        [
          1719816590.028,
          "39.3"
        ],
        [
          1719816590.528,
          "39.3"
        ],
        [
          1719816591.028,
          "38.7"
        ],
        [
          1719816591.528,
          "38.7"
        ],
        [
          1719816592.028,
          "38.7"
        ],
        [
          1719816592.528,
          "38.7"
        ],
        [
          1719816593.028,
          "38.7"
        ],
        [
          1719816593.528,
          "38.7"
        ],
        [
          1719816594.028,
          "38.7"
        ],
        [
          1719816594.528,
          "38.7"
        ],
        [
          1719816595.028,
          "38.7"
        ],
        [
          1719816595.528,
          "38.7"
        ],
        [
          1719816596.028,
          "38.7"
        ],
        [
          1719816596.528,
          "38.7"
        ],
        [
          1719816597.028,
          "38.2"
        ],
        [
          1719816597.528,
          "38.2"
        ],
        [
          1719816598.028,
          "38.2"
        ],
        [
          1719816598.528,
          "38.2"
        ],
        [
          1719816599.028,
          "38.7"
        ],
        [
          1719816599.528,
          "38.7"
        ],
        [
          1719816600.028,
          "38.7"
        ],
        [
          1719816600.528,
          "38.7"
        ],
        [
          1719816601.028,
          "39.8"
        ],
        [
          1719816601.528,
          "39.8"
        ],
        [
          1719816602.028,
          "39.8"
        ],
        [
          1719816602.528,
          "39.8"
        ],
        [
          1719816603.028,
          "40.1"
        ],
        [
          1719816603.528,
          "40.1"
        ],
        [
          1719816604.028,
          "40.1"
        ],
        [
          1719816604.528,
          "40.1"
        ],
        [
          1719816605.028,
          "40.1"
        ],
        [
          1719816605.528,
          "40.1"
        ],
        [
          1719816606.028,
          "40.1"
        ],
        [
          1719816606.528,
          "40.1"
        ],
        [
          1719816607.028,
          "40.1"
        ],
        [
          1719816607.528,
          "40.1"
        ],
        [
          1719816608.028,
          "39.4"
        ],
        [
          1719816608.528,
          "39.4"
        ],
        [
          1719816609.028,
          "39.3"
        ],
        [
          1719816609.528,
          "39.3"
        ],
        [
          1719816610.028,
          "39.3"
        ],
        [
          1719816610.528,
          "39.3"
        ],
        [
          1719816611.028,
          "37.9"
        ],
        [
          1719816611.528,
          "37.9"
        ],
        [
          1719816612.028,
          "37.9"
        ],
        [
          1719816612.528,
          "37.9"
        ],
        [
          1719816613.028,
          "38.7"
        ],
        [
          1719816613.528,
          "38.7"
        ],
        [
          1719816614.028,
          "38.7"
        ],
        [
          1719816614.528,
          "38.7"
        ],
        [
          1719816615.028,
          "38.7"
        ],
        [
          1719816615.528,
          "38.7"
        ],
        [
          1719816616.028,
          "38.7"
        ],
        [
          1719816616.528,
          "38.7"
        ],
        [
          1719816617.028,
          "38.7"
        ],
        [
          1719816617.528,
          "38.7"
        ],
        [
          1719816618.028,
          "38.7"
        ],
        [
          1719816618.528,
          "38.7"
        ],
        [
          1719816619.028,
          "38.8"
        ],
        [
          1719816619.528,
          "38.8"
        ],
        [
          1719816620.028,
          "38.8"
        ],
        [
          1719816620.528,
          "38.8"
        ],
        [
          1719816621.028,
          "38.9"
        ],
        [
          1719816621.528,
          "38.9"
        ],
        [
          1719816622.028,
          "38.9"
        ],
        [
          1719816622.528,
          "38.9"
        ],
        [
          1719816623.028,
          "38.9"
        ],
        [
          1719816623.528,
          "38.9"
        ],
        [
          1719816624.028,
          "39.3"
        ],
        [
          1719816624.528,
          "39.3"
        ],
        [
          1719816625.028,
          "38.8"
        ],
        [
          1719816625.528,
          "38.8"
        ],
        [
          1719816626.028,
          "38.8"
        ],
        [
          1719816626.528,
          "38.8"
        ],
        [
          1719816627.028,
          "38.8"
        ],
        [
          1719816627.528,
          "38.8"
        ],
        [
          1719816628.028,
          "38.8"
        ],
        [
          1719816628.528,
          "38.8"
        ],
        [
          1719816629.028,
          "38.8"
        ],
        [
          1719816629.528,
          "38.8"
        ],
        [
          1719816630.028,
          "38.8"
        ],
        [
          1719816630.528,
          "38.8"
        ],
        [
          1719816631.028,
          "38.8"
        ],
        [
          1719816631.528,
          "38.8"
        ],
        [
          1719816632.028,
          "39.8"
        ],
        [
          1719816632.528,
          "39.8"
        ],
        [
          1719816633.028,
          "39"
        ],
        [
          1719816633.528,
          "39"
        ],
        [
          1719816634.028,
          "39"
        ],
        [
          1719816634.528,
          "39"
        ],
        [
          1719816635.028,
          "39"
        ],
        [
          1719816635.528,
          "39"
        ],
        [
          1719816636.028,
          "39.2"
        ],
        [
          1719816636.528,
          "39.2"
        ],
        [
          1719816637.028,
          "39.2"
        ],
        [
          1719816637.528,
          "39.2"
        ],
        [
          1719816638.028,
          "39.2"
        ],
        [
          1719816638.528,
          "39.2"
        ],
        [
          1719816639.028,
          "39.2"
        ],
        [
          1719816639.528,
          "39.2"
        ],
        [
          1719816640.028,
          "39.2"
        ],
        [
          1719816640.528,
          "39.2"
        ],
        [
          1719816641.028,
          "38.8"
        ],
        [
          1719816641.528,
          "38.8"
        ],
        [
          1719816642.028,
          "39"
        ],
        [
          1719816642.528,
          "39"
        ],
        [
          1719816643.028,
          "39"
        ],
        [
          1719816643.528,
          "39"
        ],
        [
          1719816644.028,
          "38"
        ],
        [
          1719816644.528,
          "38"
        ],
        [
          1719816645.028,
          "39.2"
        ],
        [
          1719816645.528,
          "39.2"
        ],
        [
          1719816646.028,
          "39.2"
        ],
        [
          1719816646.528,
          "39.2"
        ],
        [
          1719816647.028,
          "39.2"
        ],
        [
          1719816647.528,
          "39.2"
        ],
        [
          1719816648.028,
          "39.5"
        ],
        [
          1719816648.528,
          "39.5"
        ],
        [
          1719816649.028,
          "39.5"
        ],
        [
          1719816649.528,
          "39.5"
        ],
        [
          1719816650.028,
          "39.5"
        ],
        [
          1719816650.528,
          "39.5"
        ],
        [
          1719816651.028,
          "39.5"
        ],
        [
          1719816651.528,
          "39.5"
        ],
        [
          1719816652.028,
          "38.7"
        ],
        [
          1719816652.528,
          "38.7"
        ],
        [
          1719816653.028,
          "38.7"
        ],
        [
          1719816653.528,
          "38.7"
        ],
        [
          1719816654.028,
          "39.1"
        ],
        [
          1719816654.528,
          "39.1"
        ],
        [
          1719816655.028,
          "39.1"
        ],
        [
          1719816655.528,
          "39.1"
        ],
        [
          1719816656.028,
          "39.4"
        ],
        [
          1719816656.528,
          "39.4"
        ],
        [
          1719816657.028,
          "38"
        ],
        [
          1719816657.528,
          "38"
        ],
        [
          1719816658.028,
          "38"
        ],
        [
          1719816658.528,
          "38"
        ],
        [
          1719816659.028,
          "38"
        ],
        [
          1719816659.528,
          "38"
        ],
        [
          1719816660.028,
          "38"
        ],
        [
          1719816660.528,
          "38"
        ],
        [
          1719816661.028,
          "38"
        ],
        [
          1719816661.528,
          "38"
        ],
        [
          1719816662.028,
          "38"
        ],
        [
          1719816662.528,
          "38"
        ],
        [
          1719816663.028,
          "39.9"
        ],
        [
          1719816663.528,
          "39.9"
        ],
        [
          1719816664.028,
          "38.7"
        ],
        [
          1719816664.528,
          "38.7"
        ],
        [
          1719816665.028,
          "38.7"
        ],
        [
          1719816665.528,
          "38.7"
        ],
        [
          1719816666.028,
          "39"
        ],
        [
          1719816666.528,
          "39"
        ],
        [
          1719816667.028,
          "39"
        ],
        [
          1719816667.528,
          "39"
        ],
        [
          1719816668.028,
          "39.8"
        ],
        [
          1719816668.528,
          "39.8"
        ],
        [
          1719816669.028,
          "39.8"
        ],
        [
          1719816669.528,
          "39.8"
        ],
        [
          1719816670.028,
          "38.5"
        ],
        [
          1719816670.528,
          "38.5"
        ],
        [
          1719816671.028,
          "38.5"
        ],
        [
          1719816671.528,
          "38.5"
        ],
        [
          1719816672.028,
          "38.5"
        ],
        [
          1719816672.528,
          "38.5"
        ],
        [
          1719816673.028,
          "38.5"
        ],
        [
          1719816673.528,
          "38.5"
        ],
        [
          1719816674.028,
          "39.8"
        ],
        [
          1719816674.528,
          "39.8"
        ],
        [
          1719816675.028,
          "39.8"
        ],
        [
          1719816675.528,
          "39.8"
        ],
        [
          1719816676.028,
          "39.1"
        ],
        [
          1719816676.528,
          "39.1"
        ],
        [
          1719816677.028,
          "39.1"
        ],
        [
          1719816677.528,
          "39.1"
        ],
        [
          1719816678.028,
          "38.4"
        ],
        [
          1719816678.528,
          "38.4"
        ],
        [
          1719816679.028,
          "38.4"
        ],
        [
          1719816679.528,
          "38.4"
        ],
        [
          1719816680.028,
          "38.4"
        ],
        [
          1719816680.528,
          "38.9"
        ],
        [
          1719816681.028,
          "38.9"
        ],
        [
          1719816681.528,
          "38.9"
        ],
        [
          1719816682.028,
          "38.9"
        ],
        [
          1719816682.528,
          "38.9"
        ],
        [
          1719816683.028,
          "38.9"
        ],
        [
          1719816683.528,
          "38.9"
        ],
        [
          1719816684.028,
          "38.9"
        ],
        [
          1719816684.528,
          "38.9"
        ],
        [
          1719816685.028,
          "38.9"
        ],
        [
          1719816685.528,
          "38.9"
        ],
        [
          1719816686.028,
          "38.9"
        ],
        [
          1719816686.528,
          "39"
        ],
        [
          1719816687.028,
          "39"
        ],
        [
          1719816687.528,
          "39"
        ],
        [
          1719816688.028,
          "39.3"
        ],
        [
          1719816688.528,
          "39.3"
        ],
        [
          1719816689.028,
          "39.3"
        ],
        [
          1719816689.528,
          "39.3"
        ],
        [
          1719816690.028,
          "39.3"
        ],
        [
          1719816690.528,
          "38"
        ],
        [
          1719816691.028,
          "38"
        ],
        [
          1719816691.528,
          "38"
        ],
        [
          1719816692.028,
          "38"
        ],
        [
          1719816692.528,
          "38.7"
        ],
        [
          1719816693.028,
          "38.7"
        ],
        [
          1719816693.528,
          "38.7"
        ],
        [
          1719816694.028,
          "38.7"
        ],
        [
          1719816694.528,
          "38.7"
        ],
        [
          1719816695.028,
          "38.7"
        ],
        [
          1719816695.528,
          "38.7"
        ],
        [
          1719816696.028,
          "38.7"
        ],
        [
          1719816696.528,
          "39.4"
        ],
        [
          1719816697.028,
          "39.4"
        ],
        [
          1719816697.528,
          "39.4"
        ],
        [
          1719816698.028,
          "39.4"
        ],
        [
          1719816698.528,
          "38.4"
        ],
        [
          1719816699.028,
          "38.4"
        ],
        [
          1719816699.528,
          "38.4"
        ],
        [
          1719816700.028,
          "38.4"
        ],
        [
          1719816700.528,
          "38.9"
        ],
        [
          1719816701.028,
          "38.9"
        ],
        [
          1719816701.528,
          "38.9"
        ],
        [
          1719816702.028,
          "38.9"
        ],
        [
          1719816702.528,
          "39.5"
        ],
        [
          1719816703.028,
          "39.5"
        ],
        [
          1719816703.528,
          "39.5"
        ],
        [
          1719816704.028,
          "39.5"
        ],
        [
          1719816704.528,
          "39.5"
        ],
        [
          1719816705.028,
          "39.5"
        ],
        [
          1719816705.528,
          "39.5"
        ],
        [
          1719816706.028,
          "39.5"
        ],
        [
          1719816706.528,
          "38.6"
        ],
        [
          1719816707.028,
          "38.6"
        ],
        [
          1719816707.528,
          "38.6"
        ],
        [
          1719816708.028,
          "38.6"
        ],
        [
          1719816708.528,
          "39.1"
        ],
        [
          1719816709.028,
          "39.1"
        ],
        [
          1719816709.528,
          "39.1"
        ],
        [
          1719816710.028,
          "39.1"
        ],
        [
          1719816710.528,
          "39.3"
        ],
        [
          1719816711.028,
          "39.3"
        ],
        [
          1719816711.528,
          "39.3"
        ],
        [
          1719816712.028,
          "39.3"
        ],
        [
          1719816712.528,
          "38.8"
        ],
        [
          1719816713.028,
          "38.8"
        ],
        [
          1719816713.528,
          "38.8"
        ],
        [
          1719816714.028,
          "38.8"
        ],
        [
          1719816714.528,
          "38.8"
        ],
        [
          1719816715.028,
          "38.8"
        ],
        [
          1719816715.528,
          "38.8"
        ],
        [
          1719816716.028,
          "38.8"
        ],
        [
          1719816716.528,
          "38.8"
        ],
        [
          1719816717.028,
          "38.8"
        ],
        [
          1719816717.528,
          "38.8"
        ],
        [
          1719816718.028,
          "38.8"
        ],
        [
          1719816718.528,
          "38.8"
        ],
        [
          1719816719.028,
          "38.8"
        ],
        [
          1719816719.528,
          "38.8"
        ],
        [
          1719816720.028,
          "38.8"
        ],
        [
          1719816720.528,
          "38.6"
        ],
        [
          1719816721.028,
          "38.6"
        ],
        [
          1719816721.528,
          "38.6"
        ],
        [
          1719816722.028,
          "38.6"
        ],
        [
          1719816722.528,
          "39.3"
        ],
        [
          1719816723.028,
          "39.3"
        ],
        [
          1719816723.528,
          "39.3"
        ],
        [
          1719816724.028,
          "39.3"
        ],
        [
          1719816724.528,
          "39.1"
        ],
        [
          1719816725.028,
          "39.1"
        ],
        [
          1719816725.528,
          "39.1"
        ],
        [
          1719816726.028,
          "39.1"
        ],
        [
          1719816726.528,
          "39.1"
        ],
        [
          1719816727.028,
          "39.1"
        ],
        [
          1719816727.528,
          "39.1"
        ],
        [
          1719816728.028,
          "39.1"
        ],
        [
          1719816728.528,
          "39.1"
        ],
        [
          1719816729.028,
          "39.1"
        ],
        [
          1719816729.528,
          "39.1"
        ],
        [
          1719816730.028,
          "39.1"
        ],
        [
          1719816730.528,
          "38.6"
        ],
        [
          1719816731.028,
          "38.6"
        ],
        [
          1719816731.528,
          "38.6"
        ],
        [
          1719816732.028,
          "38.6"
        ],
        [
          1719816732.528,
          "39"
        ],
        [
          1719816733.028,
          "39"
        ],
        [
          1719816733.528,
          "39"
        ],
        [
          1719816734.028,
          "39"
        ],
        [
          1719816734.528,
          "38.8"
        ],
        [
          1719816735.028,
          "38.8"
        ],
        [
          1719816735.528,
          "38.8"
        ],
        [
          1719816736.028,
          "38.8"
        ],
        [
          1719816736.528,
          "38.8"
        ],
        [
          1719816737.028,
          "38.8"
        ],
        [
          1719816737.528,
          "38.8"
        ],
        [
          1719816738.028,
          "38.8"
        ],
        [
          1719816738.528,
          "38.8"
        ],
        [
          1719816739.028,
          "38.8"
        ],
        [
          1719816739.528,
          "38.7"
        ],
        [
          1719816740.028,
          "38.7"
        ],
        [
          1719816740.528,
          "38.9"
        ],
        [
          1719816741.028,
          "38.9"
        ],
        [
          1719816741.528,
          "38.9"
        ],
        [
          1719816742.028,
          "38.9"
        ],
        [
          1719816742.528,
          "39.3"
        ],
        [
          1719816743.028,
          "39.3"
        ],
        [
          1719816743.528,
          "39.3"
        ],
        [
          1719816744.028,
          "39.3"
        ],
        [
          1719816744.528,
          "38.8"
        ],
        [
          1719816745.028,
          "38.8"
        ],
        [
          1719816745.528,
          "38.8"
        ],
        [
          1719816746.028,
          "38.8"
        ],
        [
          1719816746.528,
          "39.2"
        ],
        [
          1719816747.028,
          "39.2"
        ],
        [
          1719816747.528,
          "39.2"
        ],
        [
          1719816748.028,
          "39.2"
        ],
        [
          1719816748.528,
          "39.2"
        ],
        [
          1719816749.028,
          "39.2"
        ],
        [
          1719816749.528,
          "39.2"
        ],
        [
          1719816750.028,
          "39.2"
        ],
        [
          1719816750.528,
          "38.4"
        ],
        [
          1719816751.028,
          "38.4"
        ],
        [
          1719816751.528,
          "38.4"
        ],
        [
          1719816752.028,
          "38.4"
        ],
        [
          1719816752.528,
          "38.6"
        ],
        [
          1719816753.028,
          "38.6"
        ],
        [
          1719816753.528,
          "38.6"
        ],
        [
          1719816754.028,
          "38.6"
        ],
        [
          1719816754.528,
          "38.6"
        ],
        [
          1719816755.028,
          "39.5"
        ],
        [
          1719816755.528,
          "39.5"
        ],
        [
          1719816756.028,
          "39.5"
        ],
        [
          1719816756.528,
          "39.5"
        ],
        [
          1719816757.028,
          "39.2"
        ],
        [
          1719816757.528,
          "39.2"
        ],
        [
          1719816758.028,
          "39.2"
        ],
        [
          1719816758.528,
          "39.2"
        ],
        [
          1719816759.028,
          "39.2"
        ],
        [
          1719816759.528,
          "39.2"
        ],
        [
          1719816760.028,
          "39.2"
        ],
        [
          1719816760.528,
          "39.2"
        ],
        [
          1719816761.028,
          "39.2"
        ],
        [
          1719816761.528,
          "39.2"
        ],
        [
          1719816762.028,
          "39.5"
        ],
        [
          1719816762.528,
          "39.5"
        ],
        [
          1719816763.028,
          "38.8"
        ],
        [
          1719816763.528,
          "38.8"
        ],
        [
          1719816764.028,
          "38.8"
        ],
        [
          1719816764.528,
          "38.8"
        ],
        [
          1719816765.028,
          "38.6"
        ],
        [
          1719816765.528,
          "38.6"
        ],
        [
          1719816766.028,
          "38.6"
        ],
        [
          1719816766.528,
          "38.6"
        ],
        [
          1719816767.028,
          "38.6"
        ],
        [
          1719816767.528,
          "38.6"
        ],
        [
          1719816768.028,
          "38.6"
        ],
        [
          1719816768.528,
          "38.6"
        ],
        [
          1719816769.028,
          "39.3"
        ],
        [
          1719816769.528,
          "38.5"
        ],
        [
          1719816770.028,
          "38.5"
        ],
        [
          1719816770.528,
          "38.5"
        ],
        [
          1719816771.028,
          "38.5"
        ],
        [
          1719816771.528,
          "38.5"
        ],
        [
          1719816772.028,
          "38.5"
        ],
        [
          1719816772.528,
          "38.5"
        ],
        [
          1719816773.028,
          "38.5"
        ],
        [
          1719816773.528,
          "38.6"
        ],
        [
          1719816774.028,
          "38.6"
        ],
        [
          1719816774.528,
          "38.6"
        ],
        [
          1719816775.028,
          "38.6"
        ],
        [
          1719816775.528,
          "38.6"
        ],
        [
          1719816776.028,
          "38.6"
        ],
        [
          1719816776.528,
          "38.6"
        ],
        [
          1719816777.028,
          "39.4"
        ],
        [
          1719816777.528,
          "39.4"
        ],
        [
          1719816778.028,
          "39.4"
        ],
        [
          1719816778.528,
          "39.4"
        ],
        [
          1719816779.028,
          "39.4"
        ],
        [
          1719816779.528,
          "39.4"
        ],
        [
          1719816780.028,
          "39.4"
        ],
        [
          1719816780.528,
          "39.4"
        ],
        [
          1719816781.028,
          "39.4"
        ],
        [
          1719816781.528,
          "39.4"
        ],
        [
          1719816782.028,
          "39.4"
        ],
        [
          1719816782.528,
          "39.4"
        ],
        [
          1719816783.028,
          "39.4"
        ],
        [
          1719816783.528,
          "39.7"
        ],
        [
          1719816784.028,
          "39.7"
        ],
        [
          1719816784.528,
          "37.6"
        ],
        [
          1719816785.028,
          "37.6"
        ],
        [
          1719816785.528,
          "37.6"
        ],
        [
          1719816786.028,
          "37.6"
        ],
        [
          1719816786.528,
          "39.3"
        ],
        [
          1719816787.028,
          "39.3"
        ],
        [
          1719816787.528,
          "39.3"
        ],
        [
          1719816788.028,
          "39.3"
        ],
        [
          1719816788.528,
          "39.4"
        ],
        [
          1719816789.028,
          "39.4"
        ],
        [
          1719816789.528,
          "39.4"
        ],
        [
          1719816790.028,
          "39.4"
        ],
        [
          1719816790.528,
          "38.3"
        ],
        [
          1719816791.028,
          "38.3"
        ],
        [
          1719816791.528,
          "38.3"
        ],
        [
          1719816792.028,
          "38.3"
        ],
        [
          1719816792.528,
          "38.3"
        ],
        [
          1719816793.028,
          "38.3"
        ],
        [
          1719816793.528,
          "38.3"
        ],
        [
          1719816794.028,
          "38.3"
        ],
        [
          1719816794.528,
          "38.3"
        ],
        [
          1719816795.028,
          "38.3"
        ],
        [
          1719816795.528,
          "39.4"
        ],
        [
          1719816796.028,
          "39.4"
        ],
        [
          1719816796.528,
          "39.4"
        ],
        [
          1719816797.028,
          "39.1"
        ],
        [
          1719816797.528,
          "39.1"
        ],
        [
          1719816798.028,
          "39.1"
        ],
        [
          1719816798.528,
          "39.1"
        ],
        [
          1719816799.028,
          "38.6"
        ],
        [
          1719816799.528,
          "38.6"
        ],
        [
          1719816800.028,
          "38.6"
        ],
        [
          1719816800.528,
          "38.6"
        ],
        [
          1719816801.028,
          "38.2"
        ],
        [
          1719816801.528,
          "38.2"
        ],
        [
          1719816802.028,
          "38.2"
        ],
        [
          1719816802.528,
          "38.2"
        ],
        [
          1719816803.028,
          "38.2"
        ],
        [
          1719816803.528,
          "38.2"
        ],
        [
          1719816804.028,
          "38.2"
        ],
        [
          1719816804.528,
          "38.2"
        ],
        [
          1719816805.028,
          "38.2"
        ],
        [
          1719816805.528,
          "38.5"
        ],
        [
          1719816806.028,
          "38.5"
        ],
        [
          1719816806.528,
          "39.3"
        ],
        [
          1719816807.028,
          "39.3"
        ],
        [
          1719816807.528,
          "39.3"
        ],
        [
          1719816808.028,
          "39.3"
        ],
        [
          1719816808.528,
          "39.2"
        ],
        [
          1719816809.028,
          "39.2"
        ],
        [
          1719816809.528,
          "39.2"
        ],
        [
          1719816810.028,
          "39.2"
        ],
        [
          1719816810.528,
          "39.2"
        ],
        [
          1719816811.028,
          "39.2"
        ],
        [
          1719816811.528,
          "39.2"
        ],
        [
          1719816812.028,
          "39.2"
        ],
        [
          1719816812.528,
          "39.2"
        ],
        [
          1719816813.028,
          "39.2"
        ],
        [
          1719816813.528,
          "39.2"
        ],
        [
          1719816814.028,
          "39.2"
        ],
        [
          1719816814.528,
          "39.2"
        ],
        [
          1719816815.028,
          "39.2"
        ],
        [
          1719816815.528,
          "39.2"
        ],
        [
          1719816816.028,
          "39.2"
        ],
        [
          1719816816.528,
          "39.3"
        ],
        [
          1719816817.028,
          "39.3"
        ],
        [
          1719816817.528,
          "39.3"
        ],
        [
          1719816818.028,
          "39.3"
        ],
        [
          1719816818.528,
          "38.4"
        ],
        [
          1719816819.028,
          "38.4"
        ],
        [
          1719816819.528,
          "38.4"
        ],
        [
          1719816820.028,
          "38.4"
        ],
        [
          1719816820.528,
          "38.9"
        ],
        [
          1719816821.028,
          "38.9"
        ],
        [
          1719816821.528,
          "38.9"
        ],
        [
          1719816822.028,
          "38.9"
        ],
        [
          1719816822.528,
          "38.8"
        ],
        [
          1719816823.028,
          "38.8"
        ],
        [
          1719816823.528,
          "38.8"
        ],
        [
          1719816824.028,
          "38.8"
        ],
        [
          1719816824.528,
          "38.8"
        ],
        [
          1719816825.028,
          "38.8"
        ],
        [
          1719816825.528,
          "38.8"
        ],
        [
          1719816826.028,
          "38.8"
        ],
        [
          1719816826.528,
          "38.8"
        ],
        [
          1719816827.028,
          "38.8"
        ],
        [
          1719816827.528,
          "38.8"
        ],
        [
          1719816828.028,
          "39.6"
        ],
        [
          1719816828.528,
          "39.6"
        ],
        [
          1719816829.028,
          "39.6"
        ],
        [
          1719816829.528,
          "38.8"
        ],
        [
          1719816830.028,
          "38.8"
        ],
        [
          1719816830.528,
          "37.8"
        ],
        [
          1719816831.028,
          "37.8"
        ],
        [
          1719816831.528,
          "37.8"
        ],
        [
          1719816832.028,
          "37.8"
        ],
        [
          1719816832.528,
          "37.8"
        ],
        [
          1719816833.028,
          "38.5"
        ],
        [
          1719816833.528,
          "38.5"
        ],
        [
          1719816834.028,
          "38.5"
        ],
        [
          1719816834.528,
          "38.5"
        ],
        [
          1719816835.028,
          "38.5"
        ],
        [
          1719816835.528,
          "38.5"
        ],
        [
          1719816836.028,
          "38.5"
        ],
        [
          1719816836.528,
          "38.5"
        ],
        [
          1719816837.028,
          "38.5"
        ],
        [
          1719816837.528,
          "38.5"
        ],
        [
          1719816838.028,
          "38.5"
        ],
        [
          1719816838.528,
          "38.5"
        ],
        [
          1719816839.028,
          "38.9"
        ],
        [
          1719816839.528,
          "38.9"
        ],
        [
          1719816840.028,
          "38.9"
        ],
        [
          1719816840.528,
          "38.9"
        ],
        [
          1719816841.028,
          "38.9"
        ],
        [
          1719816841.528,
          "38.9"
        ],
        [
          1719816842.028,
          "39.2"
        ],
        [
          1719816842.528,
          "39.2"
        ],
        [
          1719816843.028,
          "39.2"
        ],
        [
          1719816843.528,
          "39.3"
        ],
        [
          1719816844.028,
          "39.3"
        ],
        [
          1719816844.528,
          "39.3"
        ],
        [
          1719816845.028,
          "38.6"
        ],
        [
          1719816845.528,
          "38.6"
        ],
        [
          1719816846.028,
          "38.6"
        ],
        [
          1719816846.528,
          "38.6"
        ],
        [
          1719816847.028,
          "38.6"
        ],
        [
          1719816847.528,
          "38.6"
        ],
        [
          1719816848.028,
          "38.6"
        ],
        [
          1719816848.528,
          "38.6"
        ],
        [
          1719816849.028,
          "38.6"
        ],
        [
          1719816849.528,
          "38.6"
        ],
        [
          1719816850.028,
          "38.9"
        ],
        [
          1719816850.528,
          "38.9"
        ],
        [
          1719816851.028,
          "38.7"
        ],
        [
          1719816851.528,
          "38.7"
        ],
        [
          1719816852.028,
          "38.7"
        ],
        [
          1719816852.528,
          "38.7"
        ],
        [
          1719816853.028,
          "38.7"
        ],
        [
          1719816853.528,
          "38.7"
        ],
        [
          1719816854.028,
          "39.3"
        ],
        [
          1719816854.528,
          "39.3"
        ],
        [
          1719816855.028,
          "39.3"
        ],
        [
          1719816855.528,
          "39.3"
        ],
        [
          1719816856.028,
          "39"
        ],
        [
          1719816856.528,
          "39"
        ],
        [
          1719816857.028,
          "39"
        ],
        [
          1719816857.528,
          "39"
        ],
        [
          1719816858.028,
          "39"
        ],
        [
          1719816858.528,
          "39"
        ],
        [
          1719816859.028,
          "39"
        ],
        [
          1719816859.528,
          "39"
        ],
        [
          1719816860.028,
          "39"
        ],
        [
          1719816860.528,
          "39"
        ],
        [
          1719816861.028,
          "38.6"
        ],
        [
          1719816861.528,
          "38.6"
        ],
        [
          1719816862.028,
          "39.3"
        ],
        [
          1719816862.528,
          "39.3"
        ],
        [
          1719816863.028,
          "39.3"
        ],
        [
          1719816863.528,
          "39.3"
        ],
        [
          1719816864.028,
          "37.8"
        ],
        [
          1719816864.528,
          "37.8"
        ],
        [
          1719816865.028,
          "37.8"
        ],
        [
          1719816865.528,
          "37.8"
        ],
        [
          1719816866.028,
          "38.9"
        ],
        [
          1719816866.528,
          "38.9"
        ],
        [
          1719816867.028,
          "38.9"
        ],
        [
          1719816867.528,
          "38.9"
        ],
        [
          1719816868.028,
          "39.4"
        ],
        [
          1719816868.528,
          "39.4"
        ],
        [
          1719816869.028,
          "39.4"
        ],
        [
          1719816869.528,
          "39.4"
        ],
        [
          1719816870.028,
          "39.4"
        ],
        [
          1719816870.528,
          "39.4"
        ],
        [
          1719816871.028,
          "39.4"
        ],
        [
          1719816871.528,
          "39.4"
        ],
        [
          1719816872.028,
          "38.8"
        ],
        [
          1719816872.528,
          "38.8"
        ],
        [
          1719816873.028,
          "38.8"
        ],
        [
          1719816873.528,
          "38.8"
        ],
        [
          1719816874.028,
          "38.7"
        ],
        [
          1719816874.528,
          "38.7"
        ],
        [
          1719816875.028,
          "38.7"
        ],
        [
          1719816875.528,
          "38.7"
        ],
        [
          1719816876.028,
          "39.5"
        ],
        [
          1719816876.528,
          "39.5"
        ],
        [
          1719816877.028,
          "39.5"
        ],
        [
          1719816877.528,
          "39.5"
        ],
        [
          1719816878.028,
          "38.8"
        ],
        [
          1719816878.528,
          "38.8"
        ],
        [
          1719816879.028,
          "38.8"
        ],
        [
          1719816879.528,
          "38.8"
        ],
        [
          1719816880.028,
          "38.8"
        ],
        [
          1719816880.528,
          "38.8"
        ],
        [
          1719816881.028,
          "38.8"
        ],
        [
          1719816881.528,
          "38.8"
        ],
        [
          1719816882.028,
          "38.8"
        ],
        [
          1719816882.528,
          "38.8"
        ],
        [
          1719816883.028,
          "38.7"
        ],
        [
          1719816883.528,
          "38.7"
        ],
        [
          1719816884.028,
          "38.9"
        ],
        [
          1719816884.528,
          "38.9"
        ],
        [
          1719816885.028,
          "38.9"
        ],
        [
          1719816885.528,
          "38.9"
        ],
        [
          1719816886.028,
          "38.4"
        ],
        [
          1719816886.528,
          "38.4"
        ],
        [
          1719816887.028,
          "38.4"
        ],
        [
          1719816887.528,
          "38.4"
        ],
        [
          1719816888.028,
          "39.8"
        ],
        [
          1719816888.528,
          "39.8"
        ],
        [
          1719816889.028,
          "39.8"
        ],
        [
          1719816889.528,
          "39.8"
        ],
        [
          1719816890.028,
          "38.8"
        ],
        [
          1719816890.528,
          "38.8"
        ],
        [
          1719816891.028,
          "38.8"
        ],
        [
          1719816891.528,
          "38.8"
        ],
        [
          1719816892.028,
          "38.8"
        ],
        [
          1719816892.528,
          "38.8"
        ],
        [
          1719816893.028,
          "38.8"
        ],
        [
          1719816893.528,
          "38.8"
        ],
        [
          1719816894.028,
          "39"
        ],
        [
          1719816894.528,
          "39"
        ],
        [
          1719816895.028,
          "39"
        ],
        [
          1719816895.528,
          "39"
        ],
        [
          1719816896.028,
          "38.5"
        ],
        [
          1719816896.528,
          "38.5"
        ],
        [
          1719816897.028,
          "38.5"
        ],
        [
          1719816897.528,
          "38.5"
        ],
        [
          1719816898.028,
          "38.6"
        ],
        [
          1719816898.528,
          "38.6"
        ],
        [
          1719816899.028,
          "38.6"
        ],
        [
          1719816899.528,
          "38.6"
        ],
        [
          1719816900.028,
          "39"
        ],
        [
          1719816900.528,
          "39"
        ],
        [
          1719816901.028,
          "39"
        ],
        [
          1719816901.528,
          "39"
        ],
        [
          1719816902.028,
          "39"
        ],
        [
          1719816902.528,
          "39"
        ],
        [
          1719816903.028,
          "39"
        ],
        [
          1719816903.528,
          "39"
        ],
        [
          1719816904.028,
          "39"
        ],
        [
          1719816904.528,
          "39"
        ],
        [
          1719816905.028,
          "39.9"
        ],
        [
          1719816905.528,
          "39.9"
        ],
        [
          1719816906.028,
          "38.4"
        ],
        [
          1719816906.528,
          "38.4"
        ],
        [
          1719816907.028,
          "38.4"
        ],
        [
          1719816907.528,
          "38.4"
        ],
        [
          1719816908.028,
          "40.2"
        ],
        [
          1719816908.528,
          "40.2"
        ],
        [
          1719816909.028,
          "40.2"
        ],
        [
          1719816909.528,
          "40.2"
        ],
        [
          1719816910.028,
          "38.6"
        ],
        [
          1719816910.528,
          "38.6"
        ],
        [
          1719816911.028,
          "38.6"
        ],
        [
          1719816911.528,
          "38.6"
        ],
        [
          1719816912.028,
          "38"
        ],
        [
          1719816912.528,
          "38"
        ],
        [
          1719816913.028,
          "38"
        ],
        [
          1719816913.528,
          "38"
        ],
        [
          1719816914.028,
          "38"
        ],
        [
          1719816914.528,
          "38"
        ],
        [
          1719816915.028,
          "38"
        ],
        [
          1719816915.528,
          "38"
        ],
        [
          1719816916.028,
          "39.2"
        ],
        [
          1719816916.528,
          "39.2"
        ],
        [
          1719816917.028,
          "39.2"
        ],
        [
          1719816917.528,
          "39.2"
        ],
        [
          1719816918.028,
          "38.9"
        ],
        [
          1719816918.528,
          "38.9"
        ],
        [
          1719816919.028,
          "38.9"
        ],
        [
          1719816919.528,
          "38.9"
        ],
        [
          1719816920.028,
          "38.6"
        ],
        [
          1719816920.528,
          "38.6"
        ],
        [
          1719816921.028,
          "38.6"
        ],
        [
          1719816921.528,
          "38.6"
        ],
        [
          1719816922.028,
          "39.2"
        ],
        [
          1719816922.528,
          "39.2"
        ],
        [
          1719816923.028,
          "39.2"
        ],
        [
          1719816923.528,
          "39.2"
        ],
        [
          1719816924.028,
          "39.2"
        ],
        [
          1719816924.528,
          "39.2"
        ],
        [
          1719816925.028,
          "39.2"
        ],
        [
          1719816925.528,
          "39.2"
        ],
        [
          1719816926.028,
          "39.2"
        ],
        [
          1719816926.528,
          "39.2"
        ],
        [
          1719816927.028,
          "37.9"
        ],
        [
          1719816927.528,
          "37.9"
        ],
        [
          1719816928.028,
          "39"
        ],
        [
          1719816928.528,
          "39"
        ],
        [
          1719816929.028,
          "39"
        ],
        [
          1719816929.528,
          "39"
        ],
        [
          1719816930.028,
          "38.4"
        ],
        [
          1719816930.528,
          "38.4"
        ],
        [
          1719816931.028,
          "38.4"
        ],
        [
          1719816931.528,
          "38.4"
        ],
        [
          1719816932.028,
          "39.1"
        ],
        [
          1719816932.528,
          "39.1"
        ],
        [
          1719816933.028,
          "39.1"
        ],
        [
          1719816933.528,
          "39.1"
        ],
        [
          1719816934.028,
          "39.1"
        ],
        [
          1719816934.528,
          "39.1"
        ],
        [
          1719816935.028,
          "39.1"
        ],
        [
          1719816935.528,
          "39.1"
        ],
        [
          1719816936.028,
          "39.1"
        ],
        [
          1719816936.528,
          "39.1"
        ],
        [
          1719816937.028,
          "39.1"
        ],
        [
          1719816937.528,
          "39.1"
        ],
        [
          1719816938.028,
          "38.2"
        ],
        [
          1719816938.528,
          "38.2"
        ],
        [
          1719816939.028,
          "38.2"
        ],
        [
          1719816939.528,
          "38.2"
        ],
        [
          1719816940.028,
          "39.5"
        ],
        [
          1719816940.528,
          "39.5"
        ],
        [
          1719816941.028,
          "39.5"
        ],
        [
          1719816941.528,
          "39.5"
        ],
        [
          1719816942.028,
          "38"
        ],
        [
          1719816942.528,
          "38"
        ],
        [
          1719816943.028,
          "38"
        ],
        [
          1719816943.528,
          "38"
        ],
        [
          1719816944.028,
          "38.5"
        ],
        [
          1719816944.528,
          "38.5"
        ],
        [
          1719816945.028,
          "38.5"
        ],
        [
          1719816945.528,
          "38.5"
        ],
        [
          1719816946.028,
          "38.5"
        ],
        [
          1719816946.528,
          "38.5"
        ],
        [
          1719816947.028,
          "38.5"
        ],
        [
          1719816947.528,
          "38.5"
        ],
        [
          1719816948.028,
          "38.5"
        ],
        [
          1719816948.528,
          "38.5"
        ],
        [
          1719816949.028,
          "39.7"
        ],
        [
          1719816949.528,
          "39.7"
        ],
        [
          1719816950.028,
          "38.5"
        ],
        [
          1719816950.528,
          "38.5"
        ],
        [
          1719816951.028,
          "38.5"
        ],
        [
          1719816951.528,
          "38.5"
        ],
        [
          1719816952.028,
          "38.5"
        ],
        [
          1719816952.528,
          "38.5"
        ],
        [
          1719816953.028,
          "38.5"
        ],
        [
          1719816953.528,
          "38.5"
        ],
        [
          1719816954.028,
          "39.4"
        ],
        [
          1719816954.528,
          "39.4"
        ],
        [
          1719816955.028,
          "39.4"
        ],
        [
          1719816955.528,
          "39.4"
        ],
        [
          1719816956.028,
          "38.6"
        ],
        [
          1719816956.528,
          "38.6"
        ],
        [
          1719816957.028,
          "38.6"
        ],
        [
          1719816957.528,
          "38.6"
        ],
        [
          1719816958.028,
          "38.6"
        ],
        [
          1719816958.528,
          "38.6"
        ],
        [
          1719816959.028,
          "38.6"
        ],
        [
          1719816959.528,
          "38.6"
        ],
        [
          1719816960.028,
          "39"
        ],
        [
          1719816960.528,
          "39"
        ],
        [
          1719816961.028,
          "39"
        ],
        [
          1719816961.528,
          "39"
        ],
        [
          1719816962.028,
          "39.5"
        ],
        [
          1719816962.528,
          "39.5"
        ],
        [
          1719816963.028,
          "39.5"
        ],
        [
          1719816963.528,
          "39.5"
        ],
        [
          1719816964.028,
          "38.6"
        ],
        [
          1719816964.528,
          "38.6"
        ],
        [
          1719816965.028,
          "38.6"
        ],
        [
          1719816965.528,
          "38.6"
        ],
        [
          1719816966.028,
          "39"
        ],
        [
          1719816966.528,
          "39"
        ],
        [
          1719816967.028,
          "39"
        ],
        [
          1719816967.528,
          "39"
        ],
        [
          1719816968.028,
          "39"
        ],
        [
          1719816968.528,
          "39"
        ],
        [
          1719816969.028,
          "39"
        ],
        [
          1719816969.528,
          "39"
        ],
        [
          1719816970.028,
          "39"
        ],
        [
          1719816970.528,
          "39"
        ],
        [
          1719816971.028,
          "38.8"
        ],
        [
          1719816971.528,
          "38.8"
        ],
        [
          1719816972.028,
          "37.7"
        ],
        [
          1719816972.528,
          "37.7"
        ],
        [
          1719816973.028,
          "37.7"
        ],
        [
          1719816973.528,
          "37.7"
        ],
        [
          1719816974.028,
          "38.8"
        ],
        [
          1719816974.528,
          "38.8"
        ],
        [
          1719816975.028,
          "38.8"
        ]
      ]
    }
  ]
}